zegie/__init__.py
zegie/discover/__init__.py
zegie/discover/brand.py
zegie/discover/crawler.py
zegie/discover/explore.py
zegie/discover/storage.py
zegie/images/__init__.py
zegie/images/unsplash.py
zegie/post/__init__.py
zegie/post/from_link.py
zegie/post/from_topic.py
zegie/scraper/__init__.py
zegie/scraper/base.py
zegie/scraper/native.py
zegie/scraper/web.py
zegie-0.8.0.dist-info/licenses/LICENSE.txt
zegie-0.8.0.dist-info/METADATA
zegie-0.8.0.dist-info/WHEEL
zegie-0.8.0.dist-info/top_level.txt
zegie-0.8.0.dist-info/RECORD
