Metadata-Version: 2.4
Name: zegie
Version: 0.8.0
Summary: Python SDK to Streamline Content Creation for Marketers and Creators
Home-page: https://github.com/zieeio/zegie/
Author: clivern
Author-email: hello@clivern.com
License: Apache Software License
Project-URL: Documentation, https://github.com/zieeio/zegie/
Project-URL: Source, https://github.com/zieeio/zegie/
Project-URL: Changelog, https://github.com/zieeio/zegie/blob/main/CHANGELOG.rst
Project-URL: Tracker, https://github.com/zieeio/zegie/issues
Project-URL: Download, https://pypi.org/project/zegie/#files
Platform: any
Classifier: Development Status :: 5 - Production/Stable
Classifier: Programming Language :: Python
Classifier: License :: OSI Approved :: Apache Software License
License-File: LICENSE.txt
Requires-Dist: langchain-core<=1.2.5
Requires-Dist: langchain-openai<=1.1.6
Requires-Dist: langchain-text-splitters<=1.1.0
Requires-Dist: requests<=2.32.5
Requires-Dist: urllib3<2.0
Requires-Dist: importlib-metadata; python_version < "3.8"
Requires-Dist: mechanicalsoup<=1.4.0
Requires-Dist: markdownify<=1.2.2
Dynamic: license-file
